{"version":1,"resource":"file:///home/kamisaki/Documents/anilist-tui/anilist-tui.py","entries":[{"id":"19Tg.py","timestamp":1749958361245},{"id":"fDkQ.py","timestamp":1749958458924},{"id":"b0IG.py","timestamp":1749958544104},{"id":"Kbp1.py","timestamp":1749958730983},{"id":"1Cnl.py","timestamp":1749958761653},{"id":"fhfG.py","timestamp":1749958777077},{"id":"RqRL.py","timestamp":1749958825693},{"id":"KCQ9.py","timestamp":1749959020443},{"id":"75sP.py","timestamp":1749959030868},{"id":"xyqZ.py","timestamp":1749959045145},{"id":"KLQT.py","timestamp":1749959059334},{"id":"ig7L.py","timestamp":1749959198057},{"id":"rOQn.py","timestamp":1749959273146},{"id":"HtpB.py","timestamp":1749959492913},{"id":"TCcC.py","timestamp":1749959522556},{"id":"eo2F.py","timestamp":1749959659570},{"id":"WrWg.py","timestamp":1749959707910},{"id":"nyDt.py","timestamp":1749959723223},{"id":"8jOW.py","source":"undoRedo.source","timestamp":1749959732649},{"id":"Plje.py","timestamp":1749959740072},{"id":"bYl1.py","timestamp":1749959757512},{"id":"4sCK.py","timestamp":1749959782033},{"id":"lfej.py","timestamp":1749959818830},{"id":"9R1h.py","timestamp":1749959917521},{"id":"9p8z.py","timestamp":1749959977447},{"id":"xrE0.py","timestamp":1749960026366},{"id":"GwIw.py","timestamp":1749960066484},{"id":"AxFX.py","timestamp":1749960078625},{"id":"NyYX.py","timestamp":1749960094335},{"id":"KJwp.py","timestamp":1749960131885},{"id":"dRfm.py","timestamp":1749960610315},{"id":"G34t.py","timestamp":1749960643629},{"id":"zmLz.py","timestamp":1749960838157},{"id":"YsDT.py","timestamp":1749960872467},{"id":"ZpJO.py","source":"undoRedo.source","timestamp":1749960875103},{"id":"W9aZ.py","timestamp":1749960884515},{"id":"dBQK.py","timestamp":1749960921637},{"id":"LLwX.py","timestamp":1749960949831},{"id":"Ig6M.py","timestamp":1749961003292}]}